{
  "8972e89bad9919ad83c32b48e7b9e9cd51e4789b2ccabb477e312941d5761c82.png": [
    {
      "html": "<html><body><table><thead><tr><td><b>Parameters</b></td><td><b>School A</b></td><td><b>School B</b></td></tr></thead><tbody><tr><td><b><i>q</i><sub><i>c</i></sub>, mean [ 95 <i>%</i> CI]</b></td><td><b>1.39\u00d710<sup>\u22122</sup> [ 8.10\u00d710<sup>\u22123</sup>\u22122.03\u00d710<sup>\u22122</sup>]</b></td><td><b>1.96\u00d710<sup>\u22122</sup> [ 1.11\u00d710<sup>\u22122</sup>\u22122.89\u00d710<sup>\u22122</sup>]</b></td></tr><tr><td><b><i>q</i><sub><i>g</i></sub>, mean [ 95 <i>%</i> CI]</b></td><td><b>4.36\u00d710<sup>\u22123</sup> [ 9.61\u00d710<sup>\u22124</sup>\u22128.34\u00d710<sup>\u22123</sup>]</b></td><td><b>4.61\u00d710<sup>\u22123</sup> [ 2.98\u00d710<sup>\u22124</sup>\u22121.15\u00d710<sup>\u22122</sup>]</b></td></tr><tr><td><b><i>q</i><sub><i>s</i></sub>, mean [ 95 <i>%</i> CI]</b></td><td><b>9.52\u00d710<sup>\u22124</sup> [ 2.87\u00d710<sup>\u22124</sup>\u22121.82\u00d710<sup>\u22123</sup>]</b></td><td><b>2.96\u00d710<sup>\u22123</sup> [ 1.64\u00d710<sup>\u22123</sup>\u22124.45\u00d710<sup>\u22123</sup>]</b></td></tr><tr><td><b><i>\u03b5</i>, mean [ 95 <i>%</i> CI]</b></td><td><b>3.70\u00d710<sup>\u22123</sup> [ 1.95\u00d710<sup>\u22123</sup>\u22125.69\u00d710<sup>\u22123</sup>]</b></td><td><b>2.65\u00d710<sup>\u22123</sup> [ 1.37\u00d710<sup>\u22123</sup>\u22124.20\u00d710<sup>\u22123</sup>]</b></td></tr></tbody></table></body></html>",
      "type": "simple"
    }
  ],
  "6c338e811af9402b98f215c9759761bc6c3def789a9ad83789f208d267d0006a.png": [
    {
      "html": "<html><body><table><thead><tr><td><b>Dependent variable</b></td><td colspan=\"2\"><b>ANC4</b></td><td colspan=\"2\"><b>SBA</b></td><td colspan=\"2\"><b>IFD</b></td></tr><tr><td><b>Density variable</b></td><td><b>% &quot;urban&quot;</b></td><td><b>score</b></td><td><b>% &quot;urban&quot;</b></td><td><b>score</b></td><td><b>% &quot;urban&quot;</b></td><td><b>score</b></td></tr></thead><tbody><tr><td rowspan=\"2\"><b>Density</b></td><td><b>0.003***</b></td><td><b>0.002**</b></td><td><b>0.004***</b></td><td><b>0.002**</b></td><td><b>0.004***</b></td><td><b>0.002*</b></td></tr><tr><td><b>(0.001)</b></td><td><b>(0.001)</b></td><td><b>(0.001)</b></td><td><b>(0.001)</b></td><td><b>(0.001)</b></td><td><b>(0.001)</b></td></tr><tr><td rowspan=\"2\"><b>ln(health expenditure)</b></td><td><b>0.07***</b></td><td><b>0.101***</b></td><td><b>0.073***</b></td><td><b>0.115***</b></td><td><b>0.085***</b></td><td><b>0.129***</b></td></tr><tr><td><b>(0.011)</b></td><td><b>(0.008)</b></td><td><b>(0.011)</b></td><td><b>(0.008)</b></td><td><b>(0.011)</b></td><td><b>(0.009)</b></td></tr><tr><td rowspan=\"2\"><b>Hospital beds, per capita</b></td><td><b>0.003</b></td><td><b>0.000</b></td><td><b>0.006</b></td><td><b>0.002</b></td><td><b>0.006</b></td><td><b>0.002</b></td></tr><tr><td><b>(0.006)</b></td><td><b>(0.006)</b></td><td><b>(0.006)</b></td><td><b>(0.006)</b></td><td><b>(0.006)</b></td><td><b>(0.006)</b></td></tr><tr><td rowspan=\"2\"><b>Total fertility rate</b></td><td><b>\u22120.009</b></td><td><b>\u22120.009</b></td><td><b>0.000</b></td><td><b>0.002</b></td><td><b>0.002</b></td><td><b>0.003</b></td></tr><tr><td><b>(0.011)</b></td><td><b>(0.011)</b></td><td><b>(0.010)</b></td><td><b>(0.010)</b></td><td><b>(0.010)</b></td><td><b>(0.011)</b></td></tr><tr><td rowspan=\"2\"><b># 4-wheel vehicles, per capita</b></td><td><b>0.035</b></td><td><b>0.068</b></td><td><b>0.014</b></td><td><b>0.054</b></td><td><b>0.013</b></td><td><b>0.054</b></td></tr><tr><td><b>(0.057)</b></td><td><b>(0.059)</b></td><td><b>(0.052)</b></td><td><b>(0.055)</b></td><td><b>(0.054)</b></td><td><b>(0.056)</b></td></tr><tr><td><b>Constant</b></td><td><b>0.130</b></td><td><b>0.039</b></td><td><b>0.154**</b></td><td><b>0.040</b></td><td><b>0.050</b></td><td><b>\u22120.058</b></td></tr><tr><td><b> </b></td><td><b>(0.066)</b></td><td><b>(0.070)</b></td><td><b>(0.062)</b></td><td><b>(0.068)</b></td><td><b>(0.064)</b></td><td><b>(0.070)</b></td></tr></tbody></table></body></html>",
      "type": "complex"
    }
  ],
  "8be7af498b313fcdc872c170f32425cebc75098e7c2119ea1b47a88c691245eb.png": [
    {
      "html": "<html><body><table><thead><tr><td></td><td><b>Weeks</b></td><td><b>Daily dose</b></td><td><b>Niaspan FCT dosage</b></td></tr></thead><tbody><tr><td rowspan=\"4\"><b>Initial titration schedule</b></td><td><b>0 to 4</b></td><td><b>500 mg</b></td><td><b>One 500 mg tablet at bedtime</b></td></tr><tr><td><b>5 to 8</b></td><td><b>1,000 mg</b></td><td><b>One 1,000 mg tablet or two 500 mg tablets at bedtime</b></td></tr><tr><td><b>9 to 12</b></td><td><b>1,500 mg</b></td><td><b>One 1,000 mg tablet and one 500 mg tablet at bedtime</b></td></tr><tr><td><b>13 to 24</b></td><td><b>2,000 mg</b></td><td><b>Two 1,000 mg tablets at bedtime</b></td></tr></tbody></table></body></html>",
      "type": "complex"
    }
  ],
  "60f7079ba6d811dea21e96d519da45548135509ecd489525770ce40514ffb5a0.png": [
    {
      "html": "<html><body><table><thead><tr><td><b>Combination</b></td><td><b>TP</b></td><td><b>FP</b></td><td><b>TN</b></td><td><b>FN</b></td><td><b>sensitivity (HCC = 50)</b></td><td><b>specificity (LC = 41)</b></td><td><b>TPP</b></td><td><b>TPN</b></td><td><b>LR</b></td></tr></thead><tbody><tr><td><b>afp</b></td><td><b>28</b></td><td><b>0</b></td><td><b>41</b></td><td><b>22</b></td><td><b>56.00%</b></td><td><b>100.00%</b></td><td><b>100.0%</b></td><td><b>65.10%</b></td><td><b>-</b></td></tr><tr><td><b>afp+piv</b></td><td><b>47</b></td><td><b>8</b></td><td><b>33</b></td><td><b>3</b></td><td><b>94.00%</b></td><td><b>80.50%</b></td><td><b>85.50%</b></td><td><b>91.70%</b></td><td><b>4.82</b></td></tr><tr><td><b>piv</b></td><td><b>39</b></td><td><b>8</b></td><td><b>33</b></td><td><b>11</b></td><td><b>78.00%</b></td><td><b>80.50%</b></td><td><b>83.00%</b></td><td><b>75.00%</b></td><td><b>4</b></td></tr><tr><td><b>afp+scca</b></td><td><b>36</b></td><td><b>11</b></td><td><b>30</b></td><td><b>14</b></td><td><b>72.00%</b></td><td><b>73.20%</b></td><td><b>76.60%</b></td><td><b>68.20%</b></td><td><b>2.68</b></td></tr><tr><td><b>afp+piv+scca</b></td><td><b>45</b></td><td><b>16</b></td><td><b>25</b></td><td><b>5</b></td><td><b>90.00%</b></td><td><b>61.00%</b></td><td><b>73.80%</b></td><td><b>83.30%</b></td><td><b>2.31</b></td></tr><tr><td><b>piv+scca</b></td><td><b>42</b></td><td><b>16</b></td><td><b>25</b></td><td><b>8</b></td><td><b>84.00%</b></td><td><b>61.00%</b></td><td><b>72.40%</b></td><td><b>75.80%</b></td><td><b>2.15</b></td></tr><tr><td><b>gcp+scca</b></td><td><b>36</b></td><td><b>16</b></td><td><b>25</b></td><td><b>14</b></td><td><b>72.00%</b></td><td><b>61.00%</b></td><td><b>69.20%</b></td><td><b>64.10%</b></td><td><b>1.85</b></td></tr><tr><td><b>afp+gcp</b></td><td><b>41</b></td><td><b>22</b></td><td><b>19</b></td><td><b>9</b></td><td><b>82.00%</b></td><td><b>46.30%</b></td><td><b>65.10%</b></td><td><b>67.90%</b></td><td><b>1.53</b></td></tr><tr><td><b>afp+piv+gcp</b></td><td><b>48</b></td><td><b>27</b></td><td><b>14</b></td><td><b>2</b></td><td><b>96.00%</b></td><td><b>34.10%</b></td><td><b>64.00%</b></td><td><b>87.50%</b></td><td><b>1.46</b></td></tr><tr><td><b>gcp+piv</b></td><td><b>46</b></td><td><b>27</b></td><td><b>14</b></td><td><b>4</b></td><td><b>92.00%</b></td><td><b>34.10%</b></td><td><b>63.00%</b></td><td><b>77.80%</b></td><td><b>1.4</b></td></tr><tr><td><b>all</b></td><td><b>48</b></td><td><b>31</b></td><td><b>10</b></td><td><b>2</b></td><td><b>96.00%</b></td><td><b>24.40%</b></td><td><b>60.80%</b></td><td><b>83.30%</b></td><td><b>1.27</b></td></tr><tr><td><b>gcp</b></td><td><b>34</b></td><td><b>22</b></td><td><b>19</b></td><td><b>16</b></td><td><b>68.00%</b></td><td><b>46.30%</b></td><td><b>60.70%</b></td><td><b>54.30%</b></td><td><b>1.27</b></td></tr><tr><td><b>gcp+piv+scca</b></td><td><b>47</b></td><td><b>31</b></td><td><b>10</b></td><td><b>3</b></td><td><b>94.00%</b></td><td><b>24.40%</b></td><td><b>60.30%</b></td><td><b>76.90%</b></td><td><b>1.24</b></td></tr><tr><td><b>afp+gcp+scca</b></td><td><b>36</b></td><td><b>28</b></td><td><b>13</b></td><td><b>14</b></td><td><b>72.00%</b></td><td><b>31.70%</b></td><td><b>56.30%</b></td><td><b>48.10%</b></td><td><b>1.05</b></td></tr><tr><td><b>scca</b></td><td><b>9</b></td><td><b>11</b></td><td><b>30</b></td><td><b>41</b></td><td><b>18.00%</b></td><td><b>73.20%</b></td><td><b>45.00%</b></td><td><b>42.30%</b></td><td><b>0.67</b></td></tr></tbody></table></body></html>",
      "type": "simple"
    }
  ],
  "da8512c3da0b345d6c822eda63edeec3e5bd7bbf92e06c067178beb54447138f.png": [
    {
      "html": "<html><body><table><thead><tr><td></td><td><b>Variable</b></td><td><b>OR<sup>a</sup> (IC95%)</b></td><td><b><i>p</i><sup>a</sup> value</b></td><td><b>OR<sup>B</sup> (IC95%)</b></td><td><b><i>p</i><sup>b</sup> value</b></td></tr></thead><tbody><tr><td><b>PSVI</b></td><td colspan=\"5\"><b>Part 1</b></td></tr><tr><td></td><td><b>Low PSVI</b></td><td><b>1</b></td><td><b>&lt; 0.01</b></td><td></td><td></td></tr><tr><td></td><td><b>Middle PSVI</b></td><td><b>1.21 (1.21; 1.21)</b></td><td><b>&lt; 0.01</b></td><td></td><td></td></tr><tr><td></td><td><b>High PSVI</b></td><td><b>2.50 (2.49; 2.51)</b></td><td><b>&lt; 0.01</b></td><td></td><td></td></tr><tr><td></td><td colspan=\"5\"><b>Part 2</b></td></tr><tr><td><b>Gender</b></td><td><b>Female</b></td><td><b>2.05 (2.04, 2.05)</b></td><td><b>&lt; 0.01</b></td><td><b>1.78 (1.59; 2.00)</b></td><td><b>&lt; 0.01</b></td></tr><tr><td></td><td><b>Male</b></td><td><b>1</b></td><td><b>&lt; 0.01</b></td><td><b>1</b></td><td></td></tr><tr><td><b>Skin Color</b></td><td><b>White</b></td><td><b>1</b></td><td><b>&lt; 0.01</b></td><td><b>1</b></td><td><b>&lt; 0.01</b></td></tr><tr><td></td><td><b>Black</b></td><td><b>1.51 (1.51; 1.52)</b></td><td><b>&lt; 0.01</b></td><td><b>1.56 (1.25; 1.93)</b></td><td><b>&lt; 0.01</b></td></tr><tr><td></td><td><b>Brown</b></td><td><b>1.32 (1.32; 1.32)</b></td><td><b>&lt; 0.01</b></td><td><b>1.66 (1.47; 1.88)</b></td><td></td></tr><tr><td><b>Age group</b></td><td><b>15\u201319</b></td><td><b>1.09 (1.09; 109)</b></td><td><b>&lt; 0.01</b></td><td><b>1.04 (1, 1.08)</b></td><td></td></tr><tr><td></td><td colspan=\"5\"><b>Part 3</b></td></tr><tr><td><b>Family income</b></td><td colspan=\"5\"><b>Household income (R$)</b></td></tr><tr><td></td><td><b>Up to 1.500</b></td><td><b>1.28 (1.28; 1.29)</b></td><td><b>&lt; 0.001</b></td><td><b>1.28 (1.28; 1.29)</b></td><td><b>&lt; 0.001</b></td></tr><tr><td></td><td><b>Over 1.500</b></td><td><b>1</b></td><td></td><td></td><td><b>1</b></td></tr><tr><td></td><td colspan=\"5\"><b>Part 4</b></td></tr><tr><td><b>Clinical factors</b></td><td colspan=\"5\"><b>Untreated caries lesions</b></td></tr><tr><td></td><td><b>None</b></td><td><b>1</b></td><td><b>&lt; 0.01</b></td><td><b>1</b></td><td></td></tr><tr><td></td><td><b>At least one decayed tooth</b></td><td><b>2.11 (1.89; 2.36)</b></td><td><b>&lt; 0.01</b></td><td><b>1.42 (1.25; 1.61)</b></td><td><b>&lt; 0.01</b></td></tr><tr><td></td><td colspan=\"5\"><b>Tooth loss</b></td></tr><tr><td></td><td><b>None</b></td><td><b>1</b></td><td><b>&lt; 0.01</b></td><td><b>1</b></td><td></td></tr><tr><td></td><td><b>At least one tooth loss</b></td><td><b>1.87 (1.59; 2.19)</b></td><td><b>&lt; 0.01</b></td><td><b>1.49 (1.25; 1.78)</b></td><td><b>&lt; 0.01</b></td></tr><tr><td></td><td colspan=\"5\"><b>Toothache</b></td></tr><tr><td></td><td><b>Yes</b></td><td><b>5.47 (4.80; 6.24)</b></td><td><b>&lt; 0.01</b></td><td><b>4.87 (4.25; 5.59)</b></td><td><b>&lt; 0.01</b></td></tr><tr><td></td><td><b>No</b></td><td><b>1</b></td><td><b>&lt; 0.01</b></td><td><b>1</b></td><td></td></tr><tr><td></td><td colspan=\"5\"><b>Maxillary Overjet</b></td></tr><tr><td></td><td><b>Normal</b></td><td><b>1</b></td><td></td><td><b>1</b></td><td></td></tr><tr><td></td><td><b>Moderate</b></td><td><b>1.25 (1.11; 1.40)</b></td><td><b>&lt; 0.01</b></td><td><b>1.23 (1.09; 1.40)</b></td><td><b>0.01</b></td></tr><tr><td></td><td><b>Severe</b></td><td><b>1.80 (1.28; 2.54)</b></td><td><b>&lt; 0.01</b></td><td><b>1.68 (1.15; 2.45)</b></td><td><b>0.006</b></td></tr><tr><td></td><td colspan=\"5\"><b>Cross Bite</b></td></tr><tr><td></td><td><b>Absence</b></td><td><b>1</b></td><td><b>&lt; 0.01</b></td><td></td><td></td></tr><tr><td></td><td><b>Presence</b></td><td><b>0.94 (0.74; 1.20)</b></td><td><b>0.667</b></td><td></td><td></td></tr><tr><td></td><td colspan=\"5\"><b>Open Bite</b></td></tr><tr><td></td><td><b>Mild</b></td><td><b>1</b></td><td></td><td><b>1</b></td><td></td></tr><tr><td></td><td><b>Moderate</b></td><td><b>1.34 (1.07; 1.68)</b></td><td><b>0.01</b></td><td><b>1.14 (0.89; 1.47)</b></td><td><b>0.275</b></td></tr><tr><td></td><td><b>Severe</b></td><td><b>1.28 (0.84; 1.96)</b></td><td><b>0.239</b></td><td><b>1.27 (0.80; 2.03)</b></td><td><b>0.302</b></td></tr><tr><td></td><td colspan=\"5\"><b>Presence of bleeding</b></td></tr><tr><td></td><td><b>Yes</b></td><td><b>2.09 (1.86; 2.35)</b></td><td><b>&lt; 0.01</b></td><td><b>1.45 (1.25; 1.68)</b></td><td><b>&lt; 0.01</b></td></tr><tr><td></td><td><b>No</b></td><td><b>1</b></td><td></td><td><b>1</b></td><td></td></tr><tr><td></td><td colspan=\"5\"><b>Presence of calculus</b></td></tr><tr><td></td><td><b>Yes</b></td><td><b>2.05 (1.82; 2.31)</b></td><td><b>&lt; 0.01</b></td><td><b>1.55 (1,34; 1,80)</b></td><td><b>&lt; 0.01</b></td></tr><tr><td></td><td><b>No</b></td><td><b>1</b></td><td></td><td><b>1</b></td><td></td></tr></tbody></table></body></html>",
      "type": "complex"
    }
  ],
  "c26a54401dc062f7ff2aff801c23eccf6a5c71206acd06bc029182e31ca1f01d.png": [
    {
      "html": "<html><body><table><thead><tr><td><b> </b></td><td><b>Group I(<i>n</i> = 25)</b></td><td><b>Group P(<i>n</i> = 25)</b></td><td><b><i>P</i> value</b></td></tr></thead><tbody><tr><td><b>Desaturation (SpO<sub>2</sub> &lt; 90%)</b></td><td><b>3 (12%)</b></td><td><b>2 (8%)</b></td><td><b>1.000</b></td></tr><tr><td><b>Gastric insufflations</b></td><td><b>1 (4%)</b></td><td><b>0 (0%)</b></td><td><b>1.000</b></td></tr><tr><td><b>Aspiration</b></td><td><b>0 (0%)</b></td><td><b>0 (0%)</b></td><td><b>\u2014</b></td></tr><tr><td><b>Laryngospasm</b></td><td><b>1 (4%)</b></td><td><b>1 (4%)</b></td><td><b>1.000</b></td></tr><tr><td><b>Bronchospasm</b></td><td><b>0 (0%)</b></td><td><b>0 (0%)</b></td><td><b>\u2014</b></td></tr><tr><td><b>Blood stain</b></td><td><b>0 (0%)</b></td><td><b>2 (8%)</b></td><td><b>0.490</b></td></tr></tbody></table></body></html>",
      "type": "simple"
    }
  ],
  "3df4c15b6e133af47b8de862f86279470a08b80f5332c42d7772054da865abf1.png": [
    {
      "html": "<html><body><table><thead><tr><td><b>Remaining per-base coverage after B-tail removal</b></td><td><b>Number of positions with this coverage in the ZR reference (Bv-95nt data)</b></td><td><b>Number of positions with this coverage in the PhiX reference (PhiX-95nt data)</b></td></tr></thead><tbody><tr><td><b>90 to 100%</b></td><td><b>41,130 (40.26%)</b></td><td><b>4,016 (91.65%)</b></td></tr><tr><td><b>80 to 90%</b></td><td><b>4,056 (3.97%)</b></td><td><b>266 (6.07%)</b></td></tr><tr><td><b>60 to 80%</b></td><td><b>1,711 (1.67%)</b></td><td><b>100 (2.28%)</b></td></tr><tr><td><b>40 to 60%</b></td><td><b>310 (0.30%)</b></td><td><b>0 (0.00%)</b></td></tr><tr><td><b>20 to 40%</b></td><td><b>76 (0.07%)</b></td><td><b>0 (0.00%)</b></td></tr><tr><td><b>0 to 20%</b></td><td><b>29 (0.03%)</b></td><td><b>0 (0.00%)</b></td></tr></tbody></table></body></html>",
      "type": "simple"
    }
  ],
  "f8e5e3067d00554e8de86b5f0fc0fd401ea4aa43d2cafca8f83aeb2b3c94593a.png": [
    {
      "html": "<html><body><table><thead><tr><td rowspan=\"3\"><b>Parameter</b></td><td rowspan=\"3\"><b>DF</b></td><td rowspan=\"2\" colspan=\"2\"><b>TPC</b></td><td colspan=\"6\"><b>Antioxidant Capacity</b></td></tr><tr><td colspan=\"2\"><b>ABTS</b></td><td colspan=\"2\"><b>DPPH</b></td><td colspan=\"2\"><b>CUPRAC</b></td></tr><tr><td><b><i>F</i></b></td><td><b><i>p</i> &gt; <i>F</i></b></td><td><b><i>F</i></b></td><td><b><i>p</i> &gt; <i>F</i></b></td><td><b><i>F</i></b></td><td><b><i>p</i> &gt; <i>F</i></b></td><td><b><i>F</i></b></td><td><b><i>p</i> &gt; <i>F</i></b></td></tr></thead><tbody><tr><td><b><i>\u03b2</i><sub>0</sub></b></td><td><b>1</b></td><td><b>16.90</b></td><td><b>&lt;0.01 *</b></td><td><b>16.85</b></td><td><b>&lt;0.01 *</b></td><td><b>8.91</b></td><td><b>&lt;0.01 *</b></td><td><b>16.34</b></td><td><b>&lt;0.01 *</b></td></tr><tr><td><b><i>\u03b2</i><sub>1</sub></b></td><td><b>1</b></td><td><b>0.45</b></td><td><b>0.53</b></td><td><b>7.16</b></td><td><b>0.04 *</b></td><td><b>23.92</b></td><td><b>0.00 *</b></td><td><b>12.63</b></td><td><b>0.02 *</b></td></tr><tr><td><b><i>\u03b2</i><sub>2</sub></b></td><td><b>1</b></td><td><b>1.78</b></td><td><b>0.24</b></td><td><b>0.62</b></td><td><b>0.47</b></td><td><b>1.46</b></td><td><b>0.28</b></td><td><b>0.32</b></td><td><b>0.59</b></td></tr><tr><td><b><i>\u03b2</i><sub>3</sub></b></td><td><b>1</b></td><td><b>6.47</b></td><td><b>0.05 *</b></td><td><b>1.78</b></td><td><b>0.24</b></td><td><b>2.22</b></td><td><b>0.20</b></td><td><b>2.98</b></td><td><b>0.15</b></td></tr><tr><td><b><i>\u03b2</i><sub>12</sub></b></td><td><b>1</b></td><td><b>7.24</b></td><td><b>0.04 *</b></td><td><b>0.01</b></td><td><b>0.92</b></td><td><b>5.96</b></td><td><b>0.06</b></td><td><b>0.35</b></td><td><b>0.58</b></td></tr><tr><td><b><i>\u03b2</i><sub>13</sub></b></td><td><b>1</b></td><td><b>0.02</b></td><td><b>0.89</b></td><td><b>1.07</b></td><td><b>0.35</b></td><td><b>0.35</b></td><td><b>0.58</b></td><td><b>0.00</b></td><td><b>0.99</b></td></tr><tr><td><b><i>\u03b2</i><sub>23</sub></b></td><td><b>1</b></td><td><b>0.02</b></td><td><b>0.90</b></td><td><b>0.31</b></td><td><b>0.60</b></td><td><b>0.86</b></td><td><b>0.40</b></td><td><b>0.26</b></td><td><b>0.63</b></td></tr><tr><td><b><i>\u03b2</i><sub>11</sub></b></td><td><b>1</b></td><td><b>6.65</b></td><td><b>0.05 *</b></td><td><b>7.59</b></td><td><b>0.04 *</b></td><td><b>0.85</b></td><td><b>0.40</b></td><td><b>7.26</b></td><td><b>0.04*</b></td></tr><tr><td><b><i>\u03b2</i><sub>22</sub></b></td><td><b>1</b></td><td><b>0.11</b></td><td><b>0.75</b></td><td><b>0.00</b></td><td><b>0.96</b></td><td><b>2.17</b></td><td><b>0.20</b></td><td><b>1.89</b></td><td><b>0.23</b></td></tr><tr><td><b><i>\u03b2</i><sub>33</sub></b></td><td><b>1</b></td><td><b>2.50</b></td><td><b>0.17</b></td><td><b>7.75</b></td><td><b>0.04 *</b></td><td><b>0.10</b></td><td><b>0.77</b></td><td><b>11.59</b></td><td><b>0.02 *</b></td></tr></tbody></table></body></html>",
      "type": "complex"
    }
  ],
  "903042a25ca43bbf9921d7abf1757d3c6c75af5fb987812cb41cdb01eb670685.png": [
    {
      "html": "<html><body><table><thead><tr><td><b>Medical categories</b></td><td><b>Number of species</b></td><td><b>Citations</b></td><td><b>Fic</b></td></tr></thead><tbody><tr><td><b>Tonic</b></td><td><b>5</b></td><td><b>38</b></td><td><b>0.89</b></td></tr><tr><td><b>Dermatological</b></td><td><b>4</b></td><td><b>120</b></td><td><b>0.97</b></td></tr><tr><td><b>Gastrointestinal</b></td><td><b>32</b></td><td><b>433</b></td><td><b>0.92</b></td></tr><tr><td><b>Galactagogue</b></td><td><b>8</b></td><td><b>86</b></td><td><b>0.91</b></td></tr><tr><td><b>Reproductive</b></td><td><b>11</b></td><td><b>155</b></td><td><b>0.93</b></td></tr><tr><td><b>Miscellaneous</b></td><td><b>22</b></td><td><b>201</b></td><td><b>0.89</b></td></tr><tr><td><b>Respiratory disorders</b></td><td><b>4</b></td><td><b>37</b></td><td><b>0.91</b></td></tr><tr><td><b>Fever</b></td><td><b>5</b></td><td><b>41</b></td><td><b>0.90</b></td></tr><tr><td><b>Wound healing</b></td><td><b>7</b></td><td><b>41</b></td><td><b>0.85</b></td></tr></tbody></table></body></html>",
      "type": "simple"
    }
  ],
  "70bf8d7bdd26521240c6df2c0310cd7ece22e69d598f725caf8d4247d3790079.png": [
    {
      "html": "<html><body><table><thead><tr><td><b>Marker</b></td><td><b>Peripheral stroma</b></td><td><b>Central stroma</b></td><td><b>Anterior stroma</b></td><td><b>Posterior stroma</b></td></tr></thead><tbody><tr><td><b>ABCG2</b></td><td><b>\u2212</b></td><td><b>\u2212</b></td><td><b>\u2212</b></td><td><b>\u2212</b></td></tr><tr><td><b>ABCG5</b></td><td><b>\u2212</b></td><td><b>\u2212</b></td><td><b>\u2212</b></td><td><b>\u2212</b></td></tr><tr><td><b>ALDH1A1</b></td><td><b>++</b></td><td><b>++</b></td><td><b>++</b></td><td><b>+</b></td></tr><tr><td><b><i>\u03b1</i>-Actinin</b></td><td><b>++</b></td><td><b>++</b></td><td><b>++</b></td><td><b>+</b></td></tr><tr><td><b>CD31</b></td><td><b>+</b></td><td><b>+</b></td><td><b>+</b></td><td><b>+</b></td></tr><tr><td><b>CD34</b></td><td><b>++</b></td><td><b>++</b></td><td><b>++</b></td><td><b>++</b></td></tr><tr><td><b>CD73</b></td><td><b>\u2212</b></td><td><b>\u2212</b></td><td><b>\u2212</b></td><td><b>\u2212</b></td></tr><tr><td><b>CD90</b></td><td><b>\u2212</b></td><td><b>\u2212</b></td><td><b>\u2212</b></td><td><b>\u2212</b></td></tr><tr><td><b>CD105</b></td><td><b>\u2212</b></td><td><b>\u2212</b></td><td><b>\u2212</b></td><td><b>\u2212</b></td></tr><tr><td><b>Collagen I</b></td><td><b>++</b></td><td><b>++</b></td><td><b>++</b></td><td><b>++</b></td></tr><tr><td><b>Collagen IV</b></td><td><b>\u2212</b></td><td><b>\u2212</b></td><td><b>\u2212</b></td><td><b>\u2212</b></td></tr><tr><td><b>CXCR4</b></td><td><b>\u2212</b></td><td><b>\u2212</b></td><td><b>\u2212</b></td><td><b>\u2212</b></td></tr><tr><td><b>Fibroblast marker</b></td><td><b>\u2212</b></td><td><b>\u2212</b></td><td><b>\u2212</b></td><td><b>\u2212</b></td></tr><tr><td><b>Fibronectin</b></td><td><b>\u2212</b></td><td><b>\u2212</b></td><td><b>\u2212</b></td><td><b>\u2212</b></td></tr><tr><td><b>Ki-67</b></td><td><b>\u2212</b></td><td><b>\u2212</b></td><td><b>\u2212</b></td><td><b>\u2212</b></td></tr><tr><td><b>Nestin</b></td><td><b>\u2212</b></td><td><b>\u2212</b></td><td><b>\u2212</b></td><td><b>\u2212</b></td></tr><tr><td><b>VE-Cadherin</b></td><td><b>\u2212</b></td><td><b>\u2212</b></td><td><b>\u2212</b></td><td><b>\u2212</b></td></tr><tr><td><b>Vimentin</b></td><td><b>++</b></td><td><b>++</b></td><td><b>++</b></td><td><b>++</b></td></tr></tbody></table></body></html>",
      "type": "simple"
    }
  ],
  "18e1b93b8340cf2b853cddc614226757d23d6bdeeef0a3e94530be06efbe04b2.png": [
    {
      "html": "<html><body><table><thead><tr><td></td><td colspan=\"4\"><b>Ezetimibe plus Fenofibrate</b></td><td colspan=\"4\"><b>Atorvastatin Monotherapy</b></td><td></td><td></td></tr><tr><td></td><td><b>Baseline</b></td><td><b>6 Weeks</b></td><td><b>% Change</b></td><td><b>p Value</b></td><td><b>Baseline</b></td><td><b>6 Weeks</b></td><td><b>% Change</b></td><td><b>p Value</b></td><td><b>% Difference</b></td><td><b>p Value</b></td></tr></thead><tbody><tr><td><b>Total Chol (mmol/L)</b></td><td><b>5.9</b></td><td><b>4.4</b></td><td><b>-25.1</b></td><td><b>&lt; 0.001</b></td><td><b>5.8</b></td><td><b>4.4</b></td><td><b>-24.6</b></td><td><b>&lt; 0.001</b></td><td><b>-0.4</b></td><td><b>0.806</b></td></tr><tr><td><b>LDL-C (mmol/L)</b></td><td><b>3.8</b></td><td><b>2.4</b></td><td><b>-34.6</b></td><td><b>&lt; 0.001</b></td><td><b>3.7</b></td><td><b>2.3</b></td><td><b>-36.7</b></td><td><b>&lt; 0.001</b></td><td><b>2.1</b></td><td><b>0.46</b></td></tr><tr><td><b>HDL-C (mmol/L)</b></td><td><b>1.4</b></td><td><b>1.5</b></td><td><b>10.0</b></td><td><b>0.002</b></td><td><b>1.3</b></td><td><b>1.5</b></td><td><b>8.9</b></td><td><b>0.006</b></td><td><b>1.1</b></td><td><b>0.778</b></td></tr><tr><td><b>Triglycerides (mmol/L)</b></td><td><b>1.5</b></td><td><b>1.0</b></td><td><b>-25.4</b></td><td><b>&lt; 0.001</b></td><td><b>1.6</b></td><td><b>1.4</b></td><td><b>-14.5</b></td><td><b>0.002</b></td><td><b>-11.0</b></td><td><b>0.079</b></td></tr><tr><td><b>TC:HDL Ratio</b></td><td><b>4.3</b></td><td><b>3.0</b></td><td><b>-29.0</b></td><td><b>&lt; 0.001</b></td><td><b>4.4</b></td><td><b>3.1</b></td><td><b>-28.7</b></td><td><b>&lt; 0.001</b></td><td><b>-0.2</b></td><td><b>0.904</b></td></tr><tr><td><b>Apo A</b></td><td><b>1.27</b></td><td><b>1.32</b></td><td><b>4.5</b></td><td><b>0.041</b></td><td><b>1.29</b></td><td><b>1.30</b></td><td><b>1.5</b></td><td><b>0.493</b></td><td><b>3.04</b></td><td><b>0.295</b></td></tr><tr><td><b>Apo B</b></td><td><b>1.21</b></td><td><b>0.82</b></td><td><b>-31.8</b></td><td><b>&lt; 0.001</b></td><td><b>1.19</b></td><td><b>0.82</b></td><td><b>-29.8</b></td><td><b>&lt; 0.001</b></td><td><b>-1.99</b></td><td><b>0.392</b></td></tr></tbody></table></body></html>",
      "type": "complex"
    }
  ]
}